[
  {
    "id": "0",
    "owner": "Hugo",
    "title": "Ingredients",
    "description": "Acheter des ingrédients frais au marché.",
    "date": "2022-10-29",
    "duration": "2",
    "start_time": "9",
    "color": "red"
  },
  {
    "id": "3",
    "owner": "Hugo",
    "title": "Médicament",
    "description": "S'acheter des médicaments contre les mini-pouces.",
    "date": "2022-10-29",
    "duration": "0.5",
    "start_time": "16",
    "color": "yellow"
  },
  {
    "id": "4",
    "owner": "Hugo",
    "title": "Carte",
    "description": "Ne pas oublier sa carte de la salle.",
    "date": "2022-10-29",
    "duration": "0.1",
    "start_time": "13",
    "color": "yellow"
  },
  {
    "id": "5",
    "owner": "Hugo",
    "title": "Travail",
    "description": "Horaires de travail au restaurant.",
    "date": "2022-10-29",
    "duration": "8",
    "start_time": "10",
    "color": "red"
  },
  {
    "id": "6",
    "owner": "Hugo",
    "title": "Travail",
    "description": "Horaires de travail au restaurant.",
    "date": "2022-10-25",
    "duration": "8",
    "start_time": "10",
    "color": "red"
  },
  {
    "id": "7",
    "owner": "Hugo",
    "title": "Insomnie",
    "description": "Pas réussir à dormir, encore.",
    "date": "2022-10-27",
    "duration": "5",
    "start_time": "22",
    "color": "green"
  }
]